mikrotik_swos-1.2.2.dist-info/licenses/LICENSE
swos/__init__.py
swos/core.py
swos/export_ansible_config.py
swos/field_maps.py
swos/platform.py
swos/read_switch_config.py
swos/swos_lite_map.py
swos/swos_map.py
mikrotik_swos-1.2.2.dist-info/METADATA
mikrotik_swos-1.2.2.dist-info/WHEEL
mikrotik_swos-1.2.2.dist-info/entry_points.txt
mikrotik_swos-1.2.2.dist-info/top_level.txt
mikrotik_swos-1.2.2.dist-info/RECORD
