Metadata-Version: 2.4
Name: mikrotik-swos
Version: 1.2.2
Summary: Python library and tools for managing MikroTik SwOS and SwOS Lite switches
Author: SwOS Contributors
License-Expression: MIT
Project-URL: Homepage, https://github.com/lanrat/python-mikrotik-swos
Project-URL: Repository, https://github.com/lanrat/python-mikrotik-swos
Project-URL: Issues, https://github.com/lanrat/python-mikrotik-swos/issues
Keywords: mikrotik,swos,switch,network,automation
Classifier: Development Status :: 4 - Beta
Classifier: Intended Audience :: System Administrators
Classifier: Programming Language :: Python :: 3
Classifier: Topic :: System :: Networking
Requires-Python: >=3.6
License-File: LICENSE
Requires-Dist: requests>=2.25.0
Requires-Dist: pyyaml>=5.1
Dynamic: license-file
